Metadata-Version: 1.1
Name: cpcu-nn
Version: 0.0.1
Summary: cpcu love love
Home-page: UNKNOWN
Author: phoompat
Author-email: phoompat@phoompat.com
License: UNKNOWN
Keywords: phoompat
Platform: UNKNOWN
Classifier: Intended Audience :: Education
Classifier: Programming Language :: Python :: 3
